LiSE/__init__.py
LiSE/alchemy.py
LiSE/cache.py
LiSE/character.py
LiSE/engine.py
LiSE/exc.py
LiSE/handle.py
LiSE/node.py
LiSE/portal.py
LiSE/proxy.py
LiSE/query.py
LiSE/rule.py
LiSE/util.py
LiSE/xcollections.py
LiSE/allegedb/__init__.py
LiSE/allegedb/alchemy.py
LiSE/allegedb/cache.py
LiSE/allegedb/core.py
LiSE/allegedb/graph.py
LiSE/allegedb/query.py
LiSE/allegedb/window.py
LiSE/allegedb/wrap.py
LiSE/allegedb/tests/__init__.py
LiSE/allegedb/tests/conftest.py
LiSE/allegedb/tests/test_all.py
LiSE/allegedb/tests/test_branch_plan.py
LiSE/allegedb/tests/test_load.py
LiSE/allegedb/tests/test_window.py
LiSE/examples/__init__.py
LiSE/examples/college.py
LiSE/examples/kobold.py
LiSE/examples/pathfind.py
LiSE/examples/polygons.py
LiSE/examples/sickle.py
LiSE/examples/wolfsheep.py
LiSE/server/__init__.py
LiSE/server/__main__.py
LiSE/tests/__init__.py
LiSE/tests/conftest.py
LiSE/tests/data.py
LiSE/tests/remake_college24.py
LiSE/tests/test_character.py
LiSE/tests/test_contents.py
LiSE/tests/test_examples.py
LiSE/tests/test_handle.py
LiSE/tests/test_load.py
LiSE/tests/test_msgpack.py
LiSE/tests/test_neighborhood.py
LiSE/tests/test_next_turn.py
LiSE/tests/test_performance.py
LiSE/tests/test_place.py
LiSE/tests/test_proxy.py
LiSE/tests/test_query.py
LiSE/tests/test_resume.py
LiSE/tests/test_rule.py
LiSE/tests/test_rule_poller.py
LiSE/tests/test_thing.py
LiSE-0.17.2.post1.dist-info/LICENSE
LiSE-0.17.2.post1.dist-info/METADATA
LiSE-0.17.2.post1.dist-info/WHEEL
LiSE-0.17.2.post1.dist-info/top_level.txt
LiSE-0.17.2.post1.dist-info/RECORD
