Metadata-Version: 2.1
Name: LiSE
Version: 0.17.2.post1
Summary: Life Simulator Engine
Author-email: Zachary Spector <public@zacharyspector.com>
License: GNU AFFERO GENERAL PUBLIC LICENSE
Project-URL: Homepage, https://codeberg.org/clayote/LiSE
Project-URL: Bug Tracker, https://codeberg.org/clayote/LiSE/issues
Classifier: Programming Language :: Python :: 3
Classifier: License :: OSI Approved :: GNU Affero General Public License v3
Classifier: Operating System :: OS Independent
Classifier: Topic :: Software Development :: Libraries
Classifier: Development Status :: 2 - Pre-Alpha
Requires-Python: >=3.8
License-File: LICENSE
Requires-Dist: astunparse <2,>=1.6.3
Requires-Dist: blinker <2,>=1.4
Requires-Dist: msgpack <2,>=1.0.0
Requires-Dist: networkx <4,>=2.4
Requires-Dist: sqlalchemy <3,>=1.4
Requires-Dist: numpy <3,>=1.19.5
Requires-Dist: tblib <4,>=1.7.0
Provides-Extra: server
Requires-Dist: CherryPy >=18.6.1 ; extra == 'server'
